osbot_local_stack/__init__.py
osbot_local_stack/aws/__init__.py
osbot_local_stack/aws/lambdas/__init__.py
osbot_local_stack/aws/lambdas/dev/__init__.py
osbot_local_stack/aws/lambdas/dev/hello_world.py
osbot_local_stack/aws/lambdas/dev/temp_lambda.py
osbot_local_stack/aws/lambdas/dev/with__osbot_utils.py
osbot_local_stack/aws/lambdas/dev/with__requests.py
osbot_local_stack/aws/lambdas/workflows/__init__.py
osbot_local_stack/aws/lambdas/workflows/s3_events.py
osbot_local_stack/local_stack/Local_Stack.py
osbot_local_stack/local_stack/Local_Stack__Internal.py
osbot_local_stack/local_stack/__init__.py
osbot_local_stack/testing/TestCase__Local_Stack.py
osbot_local_stack/testing/TestCase__Local_Stack__Temp_Bucket.py
osbot_local_stack/testing/TestCase__Local_Stack__Temp_Lambda.py
osbot_local_stack/testing/__init__.py
osbot_local_stack/utils/Version.py
osbot_local_stack/utils/__init__.py
osbot_local_stack/version
osbot_local_stack-0.6.0.dist-info/LICENSE
osbot_local_stack-0.6.0.dist-info/METADATA
osbot_local_stack-0.6.0.dist-info/WHEEL
osbot_local_stack-0.6.0.dist-info/RECORD
