Metadata-Version: 2.1
Name: osbot_local_stack
Version: 0.6.0
Summary: OWASP Security Bot - LLM
Home-page: https://github.com/owasp-sbot/OSBot-Local-Stack
License: MIT
Author: Dinis Cruz
Author-email: dinis.cruz@owasp.org
Requires-Python: >=3.11,<4.0
Classifier: License :: OSI Approved :: MIT License
Classifier: Programming Language :: Python :: 3
Classifier: Programming Language :: Python :: 3.11
Classifier: Programming Language :: Python :: 3.12
Requires-Dist: osbot-aws
Project-URL: Repository, https://github.com/owasp-sbot/OSBot-Local-Stack
